[
    {
        "id": 109366484418772498,
        "username": "Gigi",
        "acct": "Gigi@kolektiva.social",
        "display_name": "Gigi \ud83e\udd5a",
        "locked": true,
        "bot": false,
        "discoverable": true,
        "group": false,
        "created_at": "2022-11-18T00:00:00+00:00",
        "note": "<p>I do not understand why people posting daily capitalist affirmations keep trying to follow me. </p><p>Stop it.<br>(I mean the requests... though...\ud83e\udd37\ud83c\udffe\u200d\u2640\ufe0f)</p><p>Rustler of Goats and Jimmies.<br>Community Anarcho-Horticulturist Network.<br>Uppity AF</p><p>#\ufe0f\u20e3 \u2022 #\ufe0f\u20e3 \u2022 #\ufe0f\u20e3 \u2022 #\ufe0f\u20e3 \u2022 #\ufe0f\u20e3 \u2022 #\ufe0f\u20e3<br><a href=\"https://kolektiva.social/tags/AlertaAlertaAntifascista\" class=\"mention hashtag\" rel=\"nofollow noopener noreferrer\" target=\"_blank\">#<span>AlertaAlertaAntifascista</span></a>, <a href=\"https://kolektiva.social/tags/FashWatchCanada\" class=\"mention hashtag\" rel=\"nofollow noopener noreferrer\" target=\"_blank\">#<span>FashWatchCanada</span></a>, <a href=\"https://kolektiva.social/tags/ContainerGardening\" class=\"mention hashtag\" rel=\"nofollow noopener noreferrer\" target=\"_blank\">#<span>ContainerGardening</span></a> <a href=\"https://kolektiva.social/tags/CommunityDefence\" class=\"mention hashtag\" rel=\"nofollow noopener noreferrer\" target=\"_blank\">#<span>CommunityDefence</span></a>, <a href=\"https://kolektiva.social/tags/HousingIsAHumanRight\" class=\"mention hashtag\" rel=\"nofollow noopener noreferrer\" target=\"_blank\">#<span>HousingIsAHumanRight</span></a>, <a href=\"https://kolektiva.social/tags/TorontoActions\" class=\"mention hashtag\" rel=\"nofollow noopener noreferrer\" target=\"_blank\">#<span>TorontoActions</span></a>, <a href=\"https://kolektiva.social/tags/CarymaNgo\" class=\"mention hashtag\" rel=\"nofollow noopener noreferrer\" target=\"_blank\">#<span>CarymaNgo</span></a>, <a href=\"https://kolektiva.social/tags/antifa\" class=\"mention hashtag\" rel=\"nofollow noopener noreferrer\" target=\"_blank\">#<span>antifa</span></a>, <a href=\"https://kolektiva.social/tags/HousingForAll\" class=\"mention hashtag\" rel=\"nofollow noopener noreferrer\" target=\"_blank\">#<span>HousingForAll</span></a>, <a href=\"https://kolektiva.social/tags/fuckthepolice\" class=\"mention hashtag\" rel=\"nofollow noopener noreferrer\" target=\"_blank\">#<span>fuckthepolice</span></a>, <a href=\"https://kolektiva.social/tags/FuckShitlibs\" class=\"mention hashtag\" rel=\"nofollow noopener noreferrer\" target=\"_blank\">#<span>FuckShitlibs</span></a>, <a href=\"https://kolektiva.social/tags/PoliceDontKeepUsSafe\" class=\"mention hashtag\" rel=\"nofollow noopener noreferrer\" target=\"_blank\">#<span>PoliceDontKeepUsSafe</span></a></p>",
        "url": "https://kolektiva.social/@Gigi",
        "uri": "https://kolektiva.social/users/Gigi",
        "avatar": "https://files.mastodon.social/cache/accounts/avatars/109/366/484/418/772/498/original/7778a8d551468ad1.png",
        "avatar_static": "https://files.mastodon.social/cache/accounts/avatars/109/366/484/418/772/498/original/7778a8d551468ad1.png",
        "header": "https://files.mastodon.social/cache/accounts/headers/109/366/484/418/772/498/original/cf1d4b010e0bd478.png",
        "header_static": "https://files.mastodon.social/cache/accounts/headers/109/366/484/418/772/498/original/cf1d4b010e0bd478.png",
        "followers_count": 469,
        "following_count": 630,
        "statuses_count": 5802,
        "last_status_at": "2023-09-21T00:00:00",
        "emojis": [],
        "fields": [
            {
                "name": "Anarchism",
                "value": "is the future",
                "verified_at": null
            },
            {
                "name": "Only question:",
                "value": "harder or easier route?",
                "verified_at": null
            },
            {
                "name": "Timezone",
                "value": "UTC-5",
                "verified_at": null
            },
            {
                "name": "JustMyToots",
                "value": "<a href=\"https://justmytoots.com/@Gigi@kolektiva.social\" rel=\"nofollow noopener noreferrer\" target=\"_blank\"><span class=\"invisible\">https://</span><span class=\"ellipsis\">justmytoots.com/@Gigi@kolektiv</span><span class=\"invisible\">a.social</span></a>",
                "verified_at": null
            }
        ]
    },
    {
        "id": 109496163997949912,
        "username": "joshbuchea",
        "acct": "joshbuchea@hachyderm.io",
        "display_name": "Josh Buchea",
        "locked": false,
        "bot": false,
        "discoverable": true,
        "group": false,
        "created_at": "2022-12-11T00:00:00+00:00",
        "note": "<p>He/him\u2029</p><p>Dad, husband, Software Engineer.</p><p>\u2029Was arrested &amp; convicted of a felony for selling marijuana in 2011/2012. Changed my trajectory and transitioned to a career in tech.\u2028</p><p>Currently helping reverse climate change at a global reforestation startup. Building a mobile app with <a href=\"https://hachyderm.io/tags/ReactNative\" class=\"mention hashtag\" rel=\"nofollow noopener noreferrer\" target=\"_blank\">#<span>ReactNative</span></a>.\u2029</p><p>Living with <a href=\"https://hachyderm.io/tags/MECFS\" class=\"mention hashtag\" rel=\"nofollow noopener noreferrer\" target=\"_blank\">#<span>MECFS</span></a> since 2013, <a href=\"https://hachyderm.io/tags/LongCOVID\" class=\"mention hashtag\" rel=\"nofollow noopener noreferrer\" target=\"_blank\">#<span>LongCOVID</span></a> since 2020. \u2028<a href=\"https://hachyderm.io/tags/WearAMask\" class=\"mention hashtag\" rel=\"nofollow noopener noreferrer\" target=\"_blank\">#<span>WearAMask</span></a> <a href=\"https://hachyderm.io/tags/MaskUp\" class=\"mention hashtag\" rel=\"nofollow noopener noreferrer\" target=\"_blank\">#<span>MaskUp</span></a> <a href=\"https://hachyderm.io/tags/CovidIsNotOver\" class=\"mention hashtag\" rel=\"nofollow noopener noreferrer\" target=\"_blank\">#<span>CovidIsNotOver</span></a> <a href=\"https://hachyderm.io/tags/COVID19\" class=\"mention hashtag\" rel=\"nofollow noopener noreferrer\" target=\"_blank\">#<span>COVID19</span></a> \ud83d\ude37\u2029</p><p><a href=\"https://hachyderm.io/tags/Neurodivergent\" class=\"mention hashtag\" rel=\"nofollow noopener noreferrer\" target=\"_blank\">#<span>Neurodivergent</span></a> <a href=\"https://hachyderm.io/tags/Autistic\" class=\"mention hashtag\" rel=\"nofollow noopener noreferrer\" target=\"_blank\">#<span>Autistic</span></a> <a href=\"https://hachyderm.io/tags/ADHD\" class=\"mention hashtag\" rel=\"nofollow noopener noreferrer\" target=\"_blank\">#<span>ADHD</span></a> <a href=\"https://hachyderm.io/tags/SocialJustice\" class=\"mention hashtag\" rel=\"nofollow noopener noreferrer\" target=\"_blank\">#<span>SocialJustice</span></a> <a href=\"https://hachyderm.io/tags/ClimateCrisis\" class=\"mention hashtag\" rel=\"nofollow noopener noreferrer\" target=\"_blank\">#<span>ClimateCrisis</span></a> <a href=\"https://hachyderm.io/tags/SolarPunk\" class=\"mention hashtag\" rel=\"nofollow noopener noreferrer\" target=\"_blank\">#<span>SolarPunk</span></a> <a href=\"https://hachyderm.io/tags/Tech\" class=\"mention hashtag\" rel=\"nofollow noopener noreferrer\" target=\"_blank\">#<span>Tech</span></a> <a href=\"https://hachyderm.io/tags/OSS\" class=\"mention hashtag\" rel=\"nofollow noopener noreferrer\" target=\"_blank\">#<span>OSS</span></a> <a href=\"https://hachyderm.io/tags/IndieWeb\" class=\"mention hashtag\" rel=\"nofollow noopener noreferrer\" target=\"_blank\">#<span>IndieWeb</span></a></p>",
        "url": "https://hachyderm.io/@joshbuchea",
        "uri": "https://hachyderm.io/users/joshbuchea",
        "avatar": "https://files.mastodon.social/cache/accounts/avatars/109/496/163/997/949/912/original/2374982f9923153d.jpg",
        "avatar_static": "https://files.mastodon.social/cache/accounts/avatars/109/496/163/997/949/912/original/2374982f9923153d.jpg",
        "header": "https://files.mastodon.social/cache/accounts/headers/109/496/163/997/949/912/original/28b5d0715b1421a9.png",
        "header_static": "https://files.mastodon.social/cache/accounts/headers/109/496/163/997/949/912/original/28b5d0715b1421a9.png",
        "followers_count": 1327,
        "following_count": 5244,
        "statuses_count": 17573,
        "last_status_at": "2023-09-05T00:00:00",
        "emojis": [],
        "fields": [
            {
                "name": "Pronouns",
                "value": "he/him",
                "verified_at": null
            },
            {
                "name": "Location",
                "value": "Hawaii",
                "verified_at": null
            },
            {
                "name": "Website",
                "value": "<a href=\"https://joshbuchea.com\" target=\"_blank\" rel=\"nofollow noopener noreferrer\" translate=\"no\"><span class=\"invisible\">https://</span><span class=\"\">joshbuchea.com</span><span class=\"invisible\"></span></a>",
                "verified_at": "2023-09-13T15:05:37.033+00:00"
            },
            {
                "name": "GitHub",
                "value": "<a href=\"https://github.com/joshbuchea\" target=\"_blank\" rel=\"nofollow noopener noreferrer\" translate=\"no\"><span class=\"invisible\">https://</span><span class=\"\">github.com/joshbuchea</span><span class=\"invisible\"></span></a>",
                "verified_at": "2023-09-13T15:05:37.727+00:00"
            }
        ]
    },
    {
        "id": 109294616308246040,
        "username": "sabrinacostell3",
        "acct": "sabrinacostell3@glasgow.social",
        "display_name": "Lotta Cooties",
        "locked": false,
        "bot": false,
        "discoverable": false,
        "group": false,
        "created_at": "2022-11-06T00:00:00+00:00",
        "note": "<p>she/her</p>",
        "url": "https://glasgow.social/@sabrinacostell3",
        "uri": "https://glasgow.social/users/sabrinacostell3",
        "avatar": "https://files.mastodon.social/cache/accounts/avatars/109/294/616/308/246/040/original/d08ca39876833e5a.jpeg",
        "avatar_static": "https://files.mastodon.social/cache/accounts/avatars/109/294/616/308/246/040/original/d08ca39876833e5a.jpeg",
        "header": "https://mastodon.social/headers/original/missing.png",
        "header_static": "https://mastodon.social/headers/original/missing.png",
        "followers_count": 188,
        "following_count": 827,
        "statuses_count": 15229,
        "last_status_at": "2023-09-21T00:00:00",
        "emojis": [],
        "fields": []
    },
    {
        "id": 109707958484883554,
        "username": "wjd",
        "acct": "wjd@pkm.social",
        "display_name": "Will Denny (he/they)",
        "locked": true,
        "bot": false,
        "discoverable": true,
        "group": false,
        "created_at": "2023-01-18T00:00:00+00:00",
        "note": "<p>Academic support person for emerging multilingual college students.</p>",
        "url": "https://pkm.social/@wjd",
        "uri": "https://pkm.social/users/wjd",
        "avatar": "https://files.mastodon.social/cache/accounts/avatars/109/707/958/484/883/554/original/13654d6b962ae786.jpg",
        "avatar_static": "https://files.mastodon.social/cache/accounts/avatars/109/707/958/484/883/554/original/13654d6b962ae786.jpg",
        "header": "https://files.mastodon.social/cache/accounts/headers/109/707/958/484/883/554/original/116fd339f4944b67.png",
        "header_static": "https://files.mastodon.social/cache/accounts/headers/109/707/958/484/883/554/original/116fd339f4944b67.png",
        "followers_count": 29,
        "following_count": 71,
        "statuses_count": 348,
        "last_status_at": "2023-09-20T00:00:00",
        "emojis": [],
        "fields": [
            {
                "name": "GitHub",
                "value": "<a href=\"https://github.com/wjdenny\" rel=\"nofollow noopener noreferrer\" target=\"_blank\"><span class=\"invisible\">https://</span><span class=\"\">github.com/wjdenny</span><span class=\"invisible\"></span></a>",
                "verified_at": null
            },
            {
                "name": "Blog",
                "value": "<a href=\"https://www.wjdenny.com\" rel=\"nofollow noopener noreferrer\" target=\"_blank\"><span class=\"invisible\">https://www.</span><span class=\"\">wjdenny.com</span><span class=\"invisible\"></span></a>",
                "verified_at": null
            }
        ]
    },
    {
        "id": 109316679177569675,
        "username": "heydavidbailey",
        "acct": "heydavidbailey@mastodon.cloud",
        "display_name": "Daybed Baby",
        "locked": false,
        "bot": false,
        "discoverable": true,
        "group": false,
        "created_at": "2022-11-10T00:00:00+00:00",
        "note": "<p>All my fits I print as news\u2122<br>Person, woman, man, camera, TV in Portland, Oregon<br><a href=\"https://mastodon.cloud/tags/BuyNothingNew\" class=\"mention hashtag\" rel=\"nofollow noopener noreferrer\" target=\"_blank\">#<span>BuyNothingNew</span></a> <a href=\"https://mastodon.cloud/tags/WearMasksSaveLives\" class=\"mention hashtag\" rel=\"nofollow noopener noreferrer\" target=\"_blank\">#<span>WearMasksSaveLives</span></a> <a href=\"https://mastodon.cloud/tags/FuckCars\" class=\"mention hashtag\" rel=\"nofollow noopener noreferrer\" target=\"_blank\">#<span>FuckCars</span></a> <a href=\"https://mastodon.cloud/tags/eBikes\" class=\"mention hashtag\" rel=\"nofollow noopener noreferrer\" target=\"_blank\">#<span>eBikes</span></a> <a href=\"https://mastodon.cloud/tags/PDX\" class=\"mention hashtag\" rel=\"nofollow noopener noreferrer\" target=\"_blank\">#<span>PDX</span></a> <a href=\"https://mastodon.cloud/tags/MastodonMusic\" class=\"mention hashtag\" rel=\"nofollow noopener noreferrer\" target=\"_blank\">#<span>MastodonMusic</span></a> <a href=\"https://mastodon.cloud/tags/SmellsLikePop\" class=\"mention hashtag\" rel=\"nofollow noopener noreferrer\" target=\"_blank\">#<span>SmellsLikePop</span></a></p>",
        "url": "https://mastodon.cloud/@heydavidbailey",
        "uri": "https://mastodon.cloud/users/heydavidbailey",
        "avatar": "https://files.mastodon.social/cache/accounts/avatars/109/316/679/177/569/675/original/32754b8c42ca5bbb.jpg",
        "avatar_static": "https://files.mastodon.social/cache/accounts/avatars/109/316/679/177/569/675/original/32754b8c42ca5bbb.jpg",
        "header": "https://files.mastodon.social/cache/accounts/headers/109/316/679/177/569/675/original/9736b807bcc51209.jpeg",
        "header_static": "https://files.mastodon.social/cache/accounts/headers/109/316/679/177/569/675/original/9736b807bcc51209.jpeg",
        "followers_count": 79,
        "following_count": 268,
        "statuses_count": 852,
        "last_status_at": "2023-09-17T00:00:00",
        "emojis": [],
        "fields": [
            {
                "name": "Twatter",
                "value": "<a href=\"https://twitter.com/heydavidbailey\" rel=\"nofollow noopener noreferrer\" target=\"_blank\"><span class=\"invisible\">https://</span><span class=\"\">twitter.com/heydavidbailey</span><span class=\"invisible\"></span></a>",
                "verified_at": null
            },
            {
                "name": "Instant",
                "value": "<a href=\"https://www.instagram.com/heydavidbailey/\" rel=\"nofollow noopener noreferrer\" target=\"_blank\"><span class=\"invisible\">https://www.</span><span class=\"\">instagram.com/heydavidbailey/</span><span class=\"invisible\"></span></a>",
                "verified_at": null
            },
            {
                "name": "Logo-a-go-go",
                "value": "<a href=\"https://www.dbdpdx.com\" rel=\"nofollow noopener noreferrer\" target=\"_blank\"><span class=\"invisible\">https://www.</span><span class=\"\">dbdpdx.com</span><span class=\"invisible\"></span></a>",
                "verified_at": null
            }
        ]
    },
    {
        "id": 109518280405907309,
        "username": "BernieDoesIt",
        "acct": "BernieDoesIt@mstdn.social",
        "display_name": "Bernie Does It",
        "locked": false,
        "bot": false,
        "discoverable": true,
        "group": false,
        "created_at": "2022-12-15T00:00:00+00:00",
        "note": "<p>Bernie doesn't just have the best platform; he is the pragmatic choice because <a href=\"https://mstdn.social/tags/BernieGetsThingsDone\" class=\"mention hashtag\" rel=\"nofollow noopener noreferrer\" target=\"_blank\">#<span>BernieGetsThingsDone</span></a> even against intense opposition.</p>",
        "url": "https://mstdn.social/@BernieDoesIt",
        "uri": "https://mstdn.social/users/BernieDoesIt",
        "avatar": "https://files.mastodon.social/cache/accounts/avatars/109/518/280/405/907/309/original/4f19156e44f6c29a.jpg",
        "avatar_static": "https://files.mastodon.social/cache/accounts/avatars/109/518/280/405/907/309/original/4f19156e44f6c29a.jpg",
        "header": "https://mastodon.social/headers/original/missing.png",
        "header_static": "https://mastodon.social/headers/original/missing.png",
        "followers_count": 447,
        "following_count": 664,
        "statuses_count": 31476,
        "last_status_at": "2023-09-21T00:00:00",
        "emojis": [],
        "fields": []
    },
    {
        "id": 109325773859142054,
        "username": "Mama_H",
        "acct": "Mama_H@climatejustice.social",
        "display_name": "Mama H",
        "locked": false,
        "bot": false,
        "discoverable": false,
        "group": false,
        "created_at": "2022-11-11T00:00:00+00:00",
        "note": "",
        "url": "https://climatejustice.social/@Mama_H",
        "uri": "https://climatejustice.social/users/Mama_H",
        "avatar": "https://files.mastodon.social/cache/accounts/avatars/109/325/773/859/142/054/original/c660e311e3bbd7d1.jpg",
        "avatar_static": "https://files.mastodon.social/cache/accounts/avatars/109/325/773/859/142/054/original/c660e311e3bbd7d1.jpg",
        "header": "https://mastodon.social/headers/original/missing.png",
        "header_static": "https://mastodon.social/headers/original/missing.png",
        "followers_count": 104,
        "following_count": 308,
        "statuses_count": 3405,
        "last_status_at": "2023-09-21T00:00:00",
        "emojis": [],
        "fields": []
    },
    {
        "id": 109531356132299054,
        "username": "mlippert",
        "acct": "mlippert@vmst.io",
        "display_name": "Mike",
        "locked": false,
        "bot": false,
        "discoverable": true,
        "group": false,
        "created_at": "2022-12-17T00:00:00+00:00",
        "note": "<p>FOSS advocate, copyright minimalist, years of software development, full time linux user since Windows 8</p><p><a href=\"https://justmytoots.com/@mlippert@vmst.io\" rel=\"nofollow noopener noreferrer\" translate=\"no\" target=\"_blank\"><span class=\"invisible\">https://</span><span class=\"ellipsis\">justmytoots.com/@mlippert@vmst</span><span class=\"invisible\">.io</span></a></p>",
        "url": "https://vmst.io/@mlippert",
        "uri": "https://vmst.io/users/mlippert",
        "avatar": "https://files.mastodon.social/cache/accounts/avatars/109/531/356/132/299/054/original/918f8d9465aad7a0.jpg",
        "avatar_static": "https://files.mastodon.social/cache/accounts/avatars/109/531/356/132/299/054/original/918f8d9465aad7a0.jpg",
        "header": "https://mastodon.social/headers/original/missing.png",
        "header_static": "https://mastodon.social/headers/original/missing.png",
        "followers_count": 75,
        "following_count": 91,
        "statuses_count": 4439,
        "last_status_at": "2023-09-21T00:00:00",
        "emojis": [],
        "fields": [
            {
                "name": "Twitter",
                "value": "@OhPrinceMikel",
                "verified_at": null
            },
            {
                "name": "searchable",
                "value": "<a href=\"https://www.tootfinder.ch\" rel=\"nofollow noopener noreferrer\" translate=\"no\" target=\"_blank\"><span class=\"invisible\">https://www.</span><span class=\"\">tootfinder.ch</span><span class=\"invisible\"></span></a>",
                "verified_at": null
            }
        ]
    },
    {
        "id": 109298426354779236,
        "username": "sshann",
        "acct": "sshann@mas.to",
        "display_name": "Oreo Speedwagon II",
        "locked": false,
        "bot": false,
        "discoverable": false,
        "group": false,
        "created_at": "2022-11-02T00:00:00+00:00",
        "note": "<p>Central Texas-based RN with a view straight into the dystopian morass that is the US health care system and Texas politics. </p><p>Yeah.  That's me in the Pikachu suit.</p><p><a href=\"https://mas.to/tags/Healthcare\" class=\"mention hashtag\" rel=\"nofollow noopener noreferrer\" target=\"_blank\">#<span>Healthcare</span></a> <a href=\"https://mas.to/tags/Tech\" class=\"mention hashtag\" rel=\"nofollow noopener noreferrer\" target=\"_blank\">#<span>Tech</span></a> <a href=\"https://mas.to/tags/Politics\" class=\"mention hashtag\" rel=\"nofollow noopener noreferrer\" target=\"_blank\">#<span>Politics</span></a> <a href=\"https://mas.to/tags/Animals\" class=\"mention hashtag\" rel=\"nofollow noopener noreferrer\" target=\"_blank\">#<span>Animals</span></a> <a href=\"https://mas.to/tags/Space\" class=\"mention hashtag\" rel=\"nofollow noopener noreferrer\" target=\"_blank\">#<span>Space</span></a> <a href=\"https://mas.to/tags/Nature\" class=\"mention hashtag\" rel=\"nofollow noopener noreferrer\" target=\"_blank\">#<span>Nature</span></a> <a href=\"https://mas.to/tags/Climate\" class=\"mention hashtag\" rel=\"nofollow noopener noreferrer\" target=\"_blank\">#<span>Climate</span></a></p>",
        "url": "https://mas.to/@sshann",
        "uri": "https://mas.to/users/sshann",
        "avatar": "https://files.mastodon.social/cache/accounts/avatars/109/298/426/354/779/236/original/986937510974fdfa.jpg",
        "avatar_static": "https://files.mastodon.social/cache/accounts/avatars/109/298/426/354/779/236/original/986937510974fdfa.jpg",
        "header": "https://files.mastodon.social/cache/accounts/headers/109/298/426/354/779/236/original/9bdb09f827e5771e.jpg",
        "header_static": "https://files.mastodon.social/cache/accounts/headers/109/298/426/354/779/236/original/9bdb09f827e5771e.jpg",
        "followers_count": 1296,
        "following_count": 3380,
        "statuses_count": 6101,
        "last_status_at": "2023-09-21T00:00:00",
        "emojis": [],
        "fields": []
    },
    {
        "id": 110316540981257456,
        "username": "Jorsh",
        "acct": "Jorsh@beige.party",
        "display_name": "Jordi (Recumbent Module)",
        "locked": false,
        "bot": false,
        "discoverable": true,
        "group": false,
        "created_at": "2023-05-05T00:00:00+00:00",
        "note": "<p>:ace_heart: \ud83e\udd18\ud83c\udde8\ud83c\udde6<br>See Pinned For Bio</p><p>SFW account (Questionable), except for fucking swears.</p><p><a href=\"https://beige.party/tags/AntiFascist\" class=\"mention hashtag\" rel=\"nofollow noopener noreferrer\" target=\"_blank\">#<span>AntiFascist</span></a> and <a href=\"https://beige.party/tags/AntiHate\" class=\"mention hashtag\" rel=\"nofollow noopener noreferrer\" target=\"_blank\">#<span>AntiHate</span></a></p><p>Avatar is myself, wearing spiked goggles, a bandana, a Mot\u00f6rhead tee shirt, headphones around my neck, and fingerless gloves. I'm grinning like a moron and flashing the heavy metal devil horns.</p><p>Header is a screenshot from Thems Fighting Herds, and depicts the cow Arizona lassoing the goat Shanty, who makes a funny face. Credit to Mane6.</p>",
        "url": "https://beige.party/@Jorsh",
        "uri": "https://beige.party/users/Jorsh",
        "avatar": "https://files.mastodon.social/cache/accounts/avatars/110/316/540/981/257/456/original/d60bb8ffbfcd62d4.jpg",
        "avatar_static": "https://files.mastodon.social/cache/accounts/avatars/110/316/540/981/257/456/original/d60bb8ffbfcd62d4.jpg",
        "header": "https://files.mastodon.social/cache/accounts/headers/110/316/540/981/257/456/original/0fdc09cb0a6d12c9.jpg",
        "header_static": "https://files.mastodon.social/cache/accounts/headers/110/316/540/981/257/456/original/0fdc09cb0a6d12c9.jpg",
        "followers_count": 954,
        "following_count": 1504,
        "statuses_count": 29965,
        "last_status_at": "2023-09-22T00:00:00",
        "emojis": [
            {
                "shortcode": "ace_heart",
                "url": "https://files.mastodon.social/cache/custom_emojis/images/000/592/408/original/9ef488aa3aee3c31.png",
                "static_url": "https://files.mastodon.social/cache/custom_emojis/images/000/592/408/static/9ef488aa3aee3c31.png",
                "visible_in_picker": true
            }
        ],
        "fields": [
            {
                "name": "PRONOUNS",
                "value": "He/Him/They",
                "verified_at": null
            },
            {
                "name": "ORIENTATION",
                "value": "Cis-Ace/Landscape",
                "verified_at": null
            },
            {
                "name": "MUSIC",
                "value": "<a href=\"https://www.last.fm/user/rainelionheart\" rel=\"nofollow noopener noreferrer\" target=\"_blank\"><span class=\"invisible\">https://www.</span><span class=\"\">last.fm/user/rainelionheart</span><span class=\"invisible\"></span></a>",
                "verified_at": null
            },
            {
                "name": "MY TOOTS",
                "value": "DOESN'T WORK",
                "verified_at": null
            }
        ]
    },
    {
        "id": 110366576668944046,
        "username": "winstonm",
        "acct": "winstonm",
        "display_name": "Winston Marlowe",
        "locked": false,
        "bot": false,
        "discoverable": null,
        "group": false,
        "created_at": "2023-05-14T00:00:00+00:00",
        "note": "<p>Former musician with bands from the 80s, blender artist, Atheist Jew, Progressive Democrat, formally on Twitter and Mastodon(but chose a bad server)</p>",
        "url": "https://mastodon.social/@winstonm",
        "uri": "https://mastodon.social/users/winstonm",
        "avatar": "https://files.mastodon.social/accounts/avatars/110/366/576/668/944/046/original/9315cbeda70d7892.jpg",
        "avatar_static": "https://files.mastodon.social/accounts/avatars/110/366/576/668/944/046/original/9315cbeda70d7892.jpg",
        "header": "https://files.mastodon.social/accounts/headers/110/366/576/668/944/046/original/5c3f4752097707ec.jpg",
        "header_static": "https://files.mastodon.social/accounts/headers/110/366/576/668/944/046/original/5c3f4752097707ec.jpg",
        "followers_count": 146,
        "following_count": 348,
        "statuses_count": 3020,
        "last_status_at": "2023-09-21T00:00:00",
        "noindex": false,
        "emojis": [],
        "roles": [],
        "fields": []
    },
    {
        "id": 109338569507713783,
        "username": "GhostOnTheHalfShell",
        "acct": "GhostOnTheHalfShell@masto.ai",
        "display_name": "GhostOnTheHalfShell",
        "locked": false,
        "bot": false,
        "discoverable": true,
        "group": false,
        "created_at": "2022-11-13T00:00:00+00:00",
        "note": "<p>opinionated lurker of the intarwebs.</p><p>used to write code, still do. c/c++, java, php, js, c#, gdscript (godot), gnawed on sql, sparql <br> embedded, ios, mac, *nix, &amp; windows billions of years ago.</p><p>tech, graphics, anything STEM<br>anything anthropology, history, linguistics <br>anything blender, gimp (although i scream using it), audacity <br>enjoys using feet/limbs<br>prefers not to be run over by cars</p><p>I drink Philz.</p><p>I do a video or so a week on yt.</p>",
        "url": "https://masto.ai/@GhostOnTheHalfShell",
        "uri": "https://masto.ai/users/GhostOnTheHalfShell",
        "avatar": "https://files.mastodon.social/cache/accounts/avatars/109/338/569/507/713/783/original/6054a93990a37eaa.jpeg",
        "avatar_static": "https://files.mastodon.social/cache/accounts/avatars/109/338/569/507/713/783/original/6054a93990a37eaa.jpeg",
        "header": "https://mastodon.social/headers/original/missing.png",
        "header_static": "https://mastodon.social/headers/original/missing.png",
        "followers_count": 1622,
        "following_count": 1548,
        "statuses_count": 4912,
        "last_status_at": "2023-09-22T00:00:00",
        "emojis": [],
        "fields": [
            {
                "name": "YouTube",
                "value": "<a href=\"https://www.youtube.com/@GhostOnTheHalfShell\" rel=\"nofollow noopener noreferrer\" target=\"_blank\"><span class=\"invisible\">https://www.</span><span class=\"ellipsis\">youtube.com/@GhostOnTheHalfShe</span><span class=\"invisible\">ll</span></a>",
                "verified_at": null
            }
        ]
    },
    {
        "id": 109300241613400435,
        "username": "chris_spackman",
        "acct": "chris_spackman@twit.social",
        "display_name": "\u30b9\u30d1\u30c3\u30af\u30de\u30f3 \u30af\u30ea\u30b9",
        "locked": false,
        "bot": false,
        "discoverable": true,
        "group": false,
        "created_at": "2022-11-05T00:00:00+00:00",
        "note": "<p>ESOL Coordinator in Columbus, Ohio, USA.<br>L1: English, L2: Japanese</p><p><a href=\"https://twit.social/tags/Linux\" class=\"mention hashtag\" rel=\"nofollow noopener noreferrer\" target=\"_blank\">#<span>Linux</span></a> user since 1998. <a href=\"https://twit.social/tags/Emacs\" class=\"mention hashtag\" rel=\"nofollow noopener noreferrer\" target=\"_blank\">#<span>Emacs</span></a> and <a href=\"https://twit.social/tags/latex\" class=\"mention hashtag\" rel=\"nofollow noopener noreferrer\" target=\"_blank\">#<span>latex</span></a> user since 1999. <a href=\"https://twit.social/tags/Gentoo\" class=\"mention hashtag\" rel=\"nofollow noopener noreferrer\" target=\"_blank\">#<span>Gentoo</span></a> is my Linux distro of choice.</p><p>Teacher of English to Speakers of Other Languages: <a href=\"https://twit.social/tags/TESOL\" class=\"mention hashtag\" rel=\"nofollow noopener noreferrer\" target=\"_blank\">#<span>TESOL</span></a>, <a href=\"https://twit.social/tags/ESOL\" class=\"mention hashtag\" rel=\"nofollow noopener noreferrer\" target=\"_blank\">#<span>ESOL</span></a>, <a href=\"https://twit.social/tags/ESL\" class=\"mention hashtag\" rel=\"nofollow noopener noreferrer\" target=\"_blank\">#<span>ESL</span></a>, <a href=\"https://twit.social/tags/EFL\" class=\"mention hashtag\" rel=\"nofollow noopener noreferrer\" target=\"_blank\">#<span>EFL</span></a>. Advocate for <a href=\"https://twit.social/tags/EnglishLearners\" class=\"mention hashtag\" rel=\"nofollow noopener noreferrer\" target=\"_blank\">#<span>EnglishLearners</span></a> (aka <a href=\"https://twit.social/tags/EMEB\" class=\"mention hashtag\" rel=\"nofollow noopener noreferrer\" target=\"_blank\">#<span>EMEB</span></a>, <a href=\"https://twit.social/tags/MLL\" class=\"mention hashtag\" rel=\"nofollow noopener noreferrer\" target=\"_blank\">#<span>MLL</span></a>, <a href=\"https://twit.social/tags/ELL\" class=\"mention hashtag\" rel=\"nofollow noopener noreferrer\" target=\"_blank\">#<span>ELL</span></a>)</p><p>Advocate for, and creator of, <a href=\"https://twit.social/tags/OpenContent\" class=\"mention hashtag\" rel=\"nofollow noopener noreferrer\" target=\"_blank\">#<span>OpenContent</span></a>, <a href=\"https://twit.social/tags/OpenEducation\" class=\"mention hashtag\" rel=\"nofollow noopener noreferrer\" target=\"_blank\">#<span>OpenEducation</span></a>, <a href=\"https://twit.social/tags/CreativeCommons\" class=\"mention hashtag\" rel=\"nofollow noopener noreferrer\" target=\"_blank\">#<span>CreativeCommons</span></a>, <a href=\"https://twit.social/tags/OER\" class=\"mention hashtag\" rel=\"nofollow noopener noreferrer\" target=\"_blank\">#<span>OER</span></a>, etc.</p><p>Lover of <a href=\"https://twit.social/tags/history\" class=\"mention hashtag\" rel=\"nofollow noopener noreferrer\" target=\"_blank\">#<span>history</span></a>, especially <a href=\"https://twit.social/tags/JapaneseHistory\" class=\"mention hashtag\" rel=\"nofollow noopener noreferrer\" target=\"_blank\">#<span>JapaneseHistory</span></a>. I studied <a href=\"https://twit.social/tags/TaishoDemocracy\" class=\"mention hashtag\" rel=\"nofollow noopener noreferrer\" target=\"_blank\">#<span>TaishoDemocracy</span></a> and <a href=\"https://twit.social/tags/OsugiSakae\" class=\"mention hashtag\" rel=\"nofollow noopener noreferrer\" target=\"_blank\">#<span>OsugiSakae</span></a> in grad school.</p>",
        "url": "https://twit.social/@chris_spackman",
        "uri": "https://twit.social/users/chris_spackman",
        "avatar": "https://files.mastodon.social/cache/accounts/avatars/109/300/241/613/400/435/original/2ce9ad19700d1c9e.png",
        "avatar_static": "https://files.mastodon.social/cache/accounts/avatars/109/300/241/613/400/435/original/2ce9ad19700d1c9e.png",
        "header": "https://files.mastodon.social/cache/accounts/headers/109/300/241/613/400/435/original/0787e409b4ee7690.png",
        "header_static": "https://files.mastodon.social/cache/accounts/headers/109/300/241/613/400/435/original/0787e409b4ee7690.png",
        "followers_count": 261,
        "following_count": 719,
        "statuses_count": 4286,
        "last_status_at": "2023-09-20T00:00:00",
        "emojis": [],
        "fields": [
            {
                "name": "Education Stuff:",
                "value": "<a href=\"https://www.chrisspackman.com\" target=\"_blank\" rel=\"nofollow noopener noreferrer\" translate=\"no\"><span class=\"invisible\">https://www.</span><span class=\"\">chrisspackman.com</span><span class=\"invisible\"></span></a>",
                "verified_at": "2023-09-18T07:45:18.909+00:00"
            },
            {
                "name": "Non-Ed Stuff",
                "value": "<a href=\"https://www.osugisakae.com\" rel=\"nofollow noopener noreferrer\" target=\"_blank\"><span class=\"invisible\">https://www.</span><span class=\"\">osugisakae.com</span><span class=\"invisible\"></span></a>",
                "verified_at": null
            },
            {
                "name": "Every Teacher's Guide to Technology*",
                "value": "<a href=\"https://www.chrisspackman.com/technology/every-sentient-beings-guide/every-teachers-guide-to-technology-e01.0.1/index.html\" rel=\"nofollow noopener noreferrer\" target=\"_blank\"><span class=\"invisible\">https://www.</span><span class=\"ellipsis\">chrisspackman.com/technology/e</span><span class=\"invisible\">very-sentient-beings-guide/every-teachers-guide-to-technology-e01.0.1/index.html</span></a>",
                "verified_at": null
            },
            {
                "name": "Every Sentient Being's Guide to Password Security",
                "value": "<a href=\"https://www.chrisspackman.com/technology/every-sentient-beings-guide/index.html\" rel=\"nofollow noopener noreferrer\" target=\"_blank\"><span class=\"invisible\">https://www.</span><span class=\"ellipsis\">chrisspackman.com/technology/e</span><span class=\"invisible\">very-sentient-beings-guide/index.html</span></a>",
                "verified_at": null
            }
        ]
    },
    {
        "id": 109295595524289727,
        "username": "Nonog",
        "acct": "Nonog@fedibird.com",
        "display_name": "Matt Willemsen",
        "locked": false,
        "bot": false,
        "discoverable": false,
        "group": false,
        "created_at": "2022-11-05T00:00:00+00:00",
        "note": "<p>Geologist from Wisconsin at home in Japan.<br>Always exploring this world.</p>",
        "url": "https://fedibird.com/@Nonog",
        "uri": "https://fedibird.com/users/Nonog",
        "avatar": "https://files.mastodon.social/cache/accounts/avatars/109/295/595/524/289/727/original/602c933758a886b7.png",
        "avatar_static": "https://files.mastodon.social/cache/accounts/avatars/109/295/595/524/289/727/original/602c933758a886b7.png",
        "header": "https://files.mastodon.social/cache/accounts/headers/109/295/595/524/289/727/original/6d08f6c5567f5d92.png",
        "header_static": "https://files.mastodon.social/cache/accounts/headers/109/295/595/524/289/727/original/6d08f6c5567f5d92.png",
        "followers_count": 1320,
        "following_count": 2805,
        "statuses_count": 5277,
        "last_status_at": "2023-09-21T00:00:00",
        "emojis": [],
        "fields": [
            {
                "name": "Verified by",
                "value": "<a href=\"https://fedified.com\" rel=\"nofollow noopener noreferrer\" target=\"_blank\"><span class=\"invisible\">https://</span><span class=\"\">fedified.com</span><span class=\"invisible\"></span></a>",
                "verified_at": null
            }
        ]
    },
    {
        "id": 110643448596382375,
        "username": "Christo",
        "acct": "Christo@mastodonapp.uk",
        "display_name": "Christo",
        "locked": false,
        "bot": false,
        "discoverable": true,
        "group": false,
        "created_at": "2023-07-01T00:00:00+00:00",
        "note": "",
        "url": "https://mastodonapp.uk/@Christo",
        "uri": "https://mastodonapp.uk/users/Christo",
        "avatar": "https://files.mastodon.social/cache/accounts/avatars/110/643/448/596/382/375/original/a0a666d4d1195ac5.jpg",
        "avatar_static": "https://files.mastodon.social/cache/accounts/avatars/110/643/448/596/382/375/original/a0a666d4d1195ac5.jpg",
        "header": "https://mastodon.social/headers/original/missing.png",
        "header_static": "https://mastodon.social/headers/original/missing.png",
        "followers_count": 550,
        "following_count": 650,
        "statuses_count": 9318,
        "last_status_at": "2023-09-21T00:00:00",
        "emojis": [],
        "fields": []
    },
    {
        "id": 109388834383069297,
        "username": "JudyOlo",
        "acct": "JudyOlo@universeodon.com",
        "display_name": "Judy Olo",
        "locked": false,
        "bot": false,
        "discoverable": false,
        "group": false,
        "created_at": "2022-11-22T00:00:00+00:00",
        "note": "<p>Love animals, nature, <a href=\"https://universeodon.com/tags/filmnoir\" class=\"mention hashtag\" rel=\"nofollow noopener noreferrer\" target=\"_blank\">#<span>filmnoir</span></a>, Golden Age of Hollywood, <a href=\"https://universeodon.com/tags/JudyGarland\" class=\"mention hashtag\" rel=\"nofollow noopener noreferrer\" target=\"_blank\">#<span>JudyGarland</span></a>. <a href=\"https://universeodon.com/tags/Catmom\" class=\"mention hashtag\" rel=\"nofollow noopener noreferrer\" target=\"_blank\">#<span>Catmom</span></a> to two 16 year feisty old lady sweeties, Liza\ud83c\udf08 and Sid. <a href=\"https://universeodon.com/tags/seniorcats\" class=\"mention hashtag\" rel=\"nofollow noopener noreferrer\" target=\"_blank\">#<span>seniorcats</span></a>.  Blue \ud83c\udf0a Missing my Liza \ud83d\ude4f</p>",
        "url": "https://universeodon.com/@JudyOlo",
        "uri": "https://universeodon.com/users/JudyOlo",
        "avatar": "https://files.mastodon.social/cache/accounts/avatars/109/388/834/383/069/297/original/92963e9631e39118.jpg",
        "avatar_static": "https://files.mastodon.social/cache/accounts/avatars/109/388/834/383/069/297/original/92963e9631e39118.jpg",
        "header": "https://files.mastodon.social/cache/accounts/headers/109/388/834/383/069/297/original/f007d7862031c295.jpg",
        "header_static": "https://files.mastodon.social/cache/accounts/headers/109/388/834/383/069/297/original/f007d7862031c295.jpg",
        "followers_count": 476,
        "following_count": 673,
        "statuses_count": 14001,
        "last_status_at": "2023-09-22T00:00:00",
        "emojis": [],
        "fields": []
    },
    {
        "id": 109364668069119362,
        "username": "Compassionatecrab",
        "acct": "Compassionatecrab@toad.social",
        "display_name": "Compassionate Crab",
        "locked": false,
        "bot": false,
        "discoverable": false,
        "group": false,
        "created_at": "2022-11-18T00:00:00+00:00",
        "note": "<p>\u201cTrue peace is not merely the absence of tension; it is the presence of justice.\u201d MLK Jr.<br><a href=\"https://toad.social/tags/VoteBlue24\" class=\"mention hashtag\" rel=\"nofollow noopener noreferrer\" target=\"_blank\">#<span>VoteBlue24</span></a> <a href=\"https://toad.social/tags/birding\" class=\"mention hashtag\" rel=\"nofollow noopener noreferrer\" target=\"_blank\">#<span>birding</span></a> <a href=\"https://toad.social/tags/LifelongDemocrat\" class=\"mention hashtag\" rel=\"nofollow noopener noreferrer\" target=\"_blank\">#<span>LifelongDemocrat</span></a> <a href=\"https://toad.social/tags/Florida\" class=\"mention hashtag\" rel=\"nofollow noopener noreferrer\" target=\"_blank\">#<span>Florida</span></a> <a href=\"https://toad.social/tags/CovidIsNotOver\" class=\"mention hashtag\" rel=\"nofollow noopener noreferrer\" target=\"_blank\">#<span>CovidIsNotOver</span></a> <a href=\"https://toad.social/tags/MaskUp\" class=\"mention hashtag\" rel=\"nofollow noopener noreferrer\" target=\"_blank\">#<span>MaskUp</span></a> <a href=\"https://toad.social/tags/GoodTrouble\" class=\"mention hashtag\" rel=\"nofollow noopener noreferrer\" target=\"_blank\">#<span>GoodTrouble</span></a></p>",
        "url": "https://toad.social/@Compassionatecrab",
        "uri": "https://toad.social/users/Compassionatecrab",
        "avatar": "https://files.mastodon.social/cache/accounts/avatars/109/364/668/069/119/362/original/10dac7383c15d768.jpg",
        "avatar_static": "https://files.mastodon.social/cache/accounts/avatars/109/364/668/069/119/362/original/10dac7383c15d768.jpg",
        "header": "https://files.mastodon.social/cache/accounts/headers/109/364/668/069/119/362/original/2be3302b5a64422e.jpg",
        "header_static": "https://files.mastodon.social/cache/accounts/headers/109/364/668/069/119/362/original/2be3302b5a64422e.jpg",
        "followers_count": 1267,
        "following_count": 2909,
        "statuses_count": 22785,
        "last_status_at": "2023-09-21T00:00:00",
        "emojis": [],
        "fields": []
    }
]